larzuk/__init__.py
larzuk/__main__.py
larzuk/commands/__init__.py
larzuk/commands/down.py
larzuk/commands/list.py
larzuk/commands/up.py
larzuk/migration.py
larzuk-1.2.0.dist-info/LICENSE
larzuk-1.2.0.dist-info/METADATA
larzuk-1.2.0.dist-info/WHEEL
larzuk-1.2.0.dist-info/entry_points.txt
larzuk-1.2.0.dist-info/RECORD
