Metadata-Version: 2.1
Name: larzuk
Version: 1.2.0
Summary: A command-line tool to help modding-as-code for game Diablo II: Resurrected.
Home-page: https://github.com/he-yaowen/larzuk
License: GPL-3.0
Author: HE Yaowen
Author-email: he.yaowen@hotmail.com
Requires-Python: >=3.8,<4.0
Classifier: License :: OSI Approved :: GNU General Public License v3 (GPLv3)
Classifier: Programming Language :: Python :: 3
Classifier: Programming Language :: Python :: 3.8
Classifier: Programming Language :: Python :: 3.9
Classifier: Programming Language :: Python :: 3.10
Classifier: Programming Language :: Python :: 3.11
Requires-Dist: click (>=8.1.3,<9.0.0)
Requires-Dist: d2txt (>=0.5.1,<0.6.0)
Requires-Dist: diff-match-patch (>=20200713,<20200714)
